LICENSE
README.md
cover.jpg
graph.jpg
manage.py
requirements.txt
setup.py
.vscode/launch.json
.vscode/settings.json
CypartaGraphqlSubscriptionsTools/.gitignore
CypartaGraphqlSubscriptionsTools/__init__.py
CypartaGraphqlSubscriptionsTools/admin.py
CypartaGraphqlSubscriptionsTools/apps.py
CypartaGraphqlSubscriptionsTools/consumers.py
CypartaGraphqlSubscriptionsTools/events.py
CypartaGraphqlSubscriptionsTools/middleware.py
CypartaGraphqlSubscriptionsTools/mixins.py
CypartaGraphqlSubscriptionsTools/models.py
CypartaGraphqlSubscriptionsTools/routing.py
CypartaGraphqlSubscriptionsTools/schema.py
CypartaGraphqlSubscriptionsTools/serialize.py
CypartaGraphqlSubscriptionsTools/urls.py
CypartaGraphqlSubscriptionsTools/utils.py
CypartaGraphqlSubscriptionsTools/views.py
CypartaGraphqlSubscriptionsTools/.github/workflows/test.yml
CypartaGraphqlSubscriptionsTools/migrations/0001_initial.py
CypartaGraphqlSubscriptionsTools/migrations/__init__.py
cypartagraphqlsubscriptionstools.egg-info/PKG-INFO
cypartagraphqlsubscriptionstools.egg-info/SOURCES.txt
cypartagraphqlsubscriptionstools.egg-info/dependency_links.txt
cypartagraphqlsubscriptionstools.egg-info/requires.txt
cypartagraphqlsubscriptionstools.egg-info/top_level.txt