Metadata-Version: 2.1
Name: cypartagraphqlsubscriptionstools
Version: 1.1.1
Summary: A CypartaGraphqlSubscriptionsTools implementation for Graphene + Django built using Django Channels +reactive programming in python (RxPY) . Provides support for model creation, mutation and deletion,and get data with websocket or path list of events name for subscriptions .
Home-page: https://cyparta.com/
Author: Cyparta Software House
Author-email: Support@cyparta.com
License: LICENSE
Project-URL: homepage, https://cyparta.com/
Project-URL: Documentation, https://github.com/Cyparta/CypartaGraphqlSubscriptionsTools
Project-URL: Source, https://github.com/Cyparta/CypartaGraphqlSubscriptionsTools
Classifier: License :: OSI Approved :: MIT License
Classifier: Programming Language :: Python
Classifier: Programming Language :: Python :: 3
Requires-Python: >=3.9
License-File: LICENSE
